README.md
setup.py
mos/__init__.py
mos/interface/__init__.py
mos/interface/interface.py
mos/interface/model.py
mos/interface/requests.py
mos_interface.egg-info/PKG-INFO
mos_interface.egg-info/SOURCES.txt
mos_interface.egg-info/dependency_links.txt
mos_interface.egg-info/not-zip-safe
mos_interface.egg-info/requires.txt
mos_interface.egg-info/top_level.txt